{
  "transferencias": [
    {
      "id": 1,
      "valor": 35,
      "destino": "1212-1",
      "data": "2020-11-04T16:30:10.710Z"
    },
    {
      "id": "2",
      "valor": 40,
      "destino": "1213-1",
      "data": "2020-11-04T21:24:10.710Z"
    },
    {
      "id": "3",
      "valor": 12.5,
      "destino": "1214-1",
      "data": "2020-11-05T21:14:10.710Z"
    },
    {
      "valor": 18963,
      "destino": "4546-3",
      "data": "2022-11-27T04:29:02.980Z",
      "id": "4BQLkJT"
    }
  ]
}